agentle/__init__.py
agentle/py.typed
agentle/agents/__init__.py
agentle/agents/agent.py
agentle/agents/agent_config.py
agentle/agents/agent_config_dict.py
agentle/agents/agent_input.py
agentle/agents/agent_pipeline.py
agentle/agents/agent_protocol.py
agentle/agents/agent_run_output.py
agentle/agents/agent_team.py
agentle/agents/context.py
agentle/agents/context_state.py
agentle/agents/execution_state.py
agentle/agents/message_history_fixer.py
agentle/agents/performance_metrics.py
agentle/agents/step.py
agentle/agents/step_metric.py
agentle/agents/suspension_manager.py
agentle/agents/a2a/__init__.py
agentle/agents/a2a/a2a_interface.py
agentle/agents/a2a/a2a_interface_options.py
agentle/agents/a2a/message_parts/__init__.py
agentle/agents/a2a/message_parts/cache_control_type.py
agentle/agents/a2a/message_parts/data_part.py
agentle/agents/a2a/message_parts/file_part.py
agentle/agents/a2a/message_parts/text_part.py
agentle/agents/a2a/message_parts/adapters/__init__.py
agentle/agents/a2a/message_parts/adapters/agent_part_to_generation_part_adapter.py
agentle/agents/a2a/message_parts/adapters/generation_part_to_agent_part_adapter.py
agentle/agents/a2a/messages/__init__.py
agentle/agents/a2a/messages/generation_message_to_message_adapter.py
agentle/agents/a2a/messages/message.py
agentle/agents/a2a/messages/message_to_generation_message_adapter.py
agentle/agents/a2a/models/__init__.py
agentle/agents/a2a/models/agent_skill.py
agentle/agents/a2a/models/agent_usage_statistics.py
agentle/agents/a2a/models/artifact.py
agentle/agents/a2a/models/authentication.py
agentle/agents/a2a/models/capabilities.py
agentle/agents/a2a/models/file.py
agentle/agents/a2a/models/json_rpc_error.py
agentle/agents/a2a/models/json_rpc_response.py
agentle/agents/a2a/models/run_state.py
agentle/agents/a2a/notifications/__init__.py
agentle/agents/a2a/notifications/push_notification_config.py
agentle/agents/a2a/notifications/task_push_notification_config.py
agentle/agents/a2a/resources/__init__.py
agentle-0.9.38.dist-info/METADATA
agentle-0.9.38.dist-info/WHEEL
agentle-0.9.38.dist-info/licenses/LICENSE
agentle-0.9.38.dist-info/RECORD
