Metadata-Version: 2.4
Name: agentle
Version: 0.9.38
Summary: ...
Author-email: Arthur Brenno <64020210+arthurbrenno@users.noreply.github.com>
License-File: LICENSE
Requires-Python: >=3.13
Requires-Dist: aiocache>=0.12.3
Requires-Dist: aiohttp>=3.11.18
Requires-Dist: aiosqlite>=0.21.0
Requires-Dist: async-lru>=2.0.5
Requires-Dist: dill>=0.4.0
Requires-Dist: duckdb>=1.3.2
Requires-Dist: google-genai>=1.14.0
Requires-Dist: html-to-markdown>=2.3.4
Requires-Dist: langfuse>=3.8.1
Requires-Dist: markitdown>=0.1.3
Requires-Dist: mcp[cli]>=1.6.0
Requires-Dist: mistune>=3.1.4
Requires-Dist: orjson>=3.11.3
Requires-Dist: pydantic>=2.11.3
Requires-Dist: pypdf2>=3.0.1
Requires-Dist: pyyaml>=6.0.2
Requires-Dist: rock-solid-base>=0.1.14
Requires-Dist: ujson>=5.10.0
